cle_rabbit/__init__.py
cle_rabbit-0.0.1.dist-info/LICENSE
cle_rabbit-0.0.1.dist-info/METADATA
cle_rabbit-0.0.1.dist-info/WHEEL
cle_rabbit-0.0.1.dist-info/top_level.txt
cle_rabbit-0.0.1.dist-info/RECORD
